{
 "actions": [],
 "creation": "2021-09-02 14:54:49.033512",
 "doctype": "DocType",
 "editable_grid": 1,
 "engine": "InnoDB",
 "field_order": [
  "key",
  "value"
 ],
 "fields": [
  {
   "fieldname": "key",
   "fieldtype": "Data",
   "in_list_view": 1,
   "label": "Key",
   "reqd": 1
  },
  {
   "fieldname": "value",
   "fieldtype": "Data",
   "in_list_view": 1,
   "label": "Value",
   "reqd": 1
  }
 ],
 "index_web_pages_for_search": 1,
 "istable": 1,
 "links": [],
 "modified": "2024-03-27 13:06:47.819210",
 "modified_by": "Administrator",
 "module": "Accounts",
 "name": "Currency Exchange Settings Details",
 "owner": "Administrator",
 "permissions": [],
 "sort_field": "creation",
 "sort_order": "DESC",
 "states": [],
 "track_changes": 1
}