{
 "allow_copy": 0, 
 "allow_events_in_timeline": 0, 
 "allow_guest_to_view": 0, 
 "allow_import": 0, 
 "allow_rename": 0, 
 "beta": 0, 
 "creation": "2013-01-10 16:34:15", 
 "custom": 0, 
 "default_print_format": "", 
 "docstatus": 0, 
 "doctype": "DocType", 
 "document_type": "Setup", 
 "editable_grid": 0, 
 "fields": [
  {
   "allow_bulk_edit": 0, 
   "allow_in_quick_entry": 0, 
   "allow_on_submit": 0, 
   "bold": 0, 
   "collapsible": 0, 
   "columns": 0, 
   "default": "Today", 
   "fieldname": "posting_date", 
   "fieldtype": "Date", 
   "hidden": 0, 
   "ignore_user_permissions": 0, 
   "ignore_xss_filter": 0, 
   "in_filter": 0, 
   "in_global_search": 0, 
   "in_list_view": 1, 
   "in_standard_filter": 0, 
   "label": "Posting Date", 
   "length": 0, 
   "no_copy": 0, 
   "permlevel": 0, 
   "precision": "", 
   "print_hide": 0, 
   "print_hide_if_no_value": 0, 
   "read_only": 0, 
   "remember_last_selected_value": 0, 
   "report_hide": 0, 
   "reqd": 1, 
   "search_index": 0, 
   "set_only_once": 0, 
   "translatable": 0, 
   "unique": 0
  }, 
  {
   "allow_bulk_edit": 0, 
   "allow_in_quick_entry": 0, 
   "allow_on_submit": 0, 
   "bold": 0, 
   "collapsible": 0, 
   "columns": 0, 
   "fieldname": "employee", 
   "fieldtype": "Link", 
   "hidden": 0, 
   "ignore_user_permissions": 0, 
   "ignore_xss_filter": 0, 
   "in_filter": 0, 
   "in_global_search": 1, 
   "in_list_view": 1, 
   "in_standard_filter": 1, 
   "label": "Employee", 
   "length": 0, 
   "no_copy": 0, 
   "oldfieldname": "employee", 
   "oldfieldtype": "Link", 
   "options": "Employee", 
   "permlevel": 0, 
   "print_hide": 0, 
   "print_hide_if_no_value": 0, 
   "read_only": 0, 
   "remember_last_selected_value": 0, 
   "report_hide": 0, 
   "reqd": 1, 
   "search_index": 1, 
   "set_only_once": 0, 
   "translatable": 0, 
   "unique": 0
  }, 
  {
   "allow_bulk_edit": 0, 
   "allow_in_quick_entry": 0, 
   "allow_on_submit": 0, 
   "bold": 0, 
   "collapsible": 0, 
   "columns": 0, 
   "fetch_from": "employee.employee_name", 
   "fieldname": "employee_name", 
   "fieldtype": "Read Only", 
   "hidden": 0, 
   "ignore_user_permissions": 0, 
   "ignore_xss_filter": 0, 
   "in_filter": 0, 
   "in_global_search": 1, 
   "in_list_view": 1, 
   "in_standard_filter": 0, 
   "label": "Employee Name", 
   "length": 0, 
   "no_copy": 0, 
   "oldfieldname": "employee_name", 
   "oldfieldtype": "Data", 
   "options": "", 
   "permlevel": 0, 
   "print_hide": 0, 
   "print_hide_if_no_value": 0, 
   "read_only": 0, 
   "remember_last_selected_value": 0, 
   "report_hide": 0, 
   "reqd": 1, 
   "search_index": 0, 
   "set_only_once": 0, 
   "translatable": 0, 
   "unique": 0
  }, 
  {
   "allow_bulk_edit": 0, 
   "allow_in_quick_entry": 0, 
   "allow_on_submit": 0, 
   "bold": 0, 
   "collapsible": 0, 
   "columns": 0, 
   "fetch_from": "employee.department", 
   "fieldname": "department", 
   "fieldtype": "Link", 
   "hidden": 0, 
   "ignore_user_permissions": 0, 
   "ignore_xss_filter": 0, 
   "in_filter": 0, 
   "in_global_search": 0, 
   "in_list_view": 0, 
   "in_standard_filter": 1, 
   "label": "Department", 
   "length": 0, 
   "no_copy": 0, 
   "oldfieldname": "department", 
   "oldfieldtype": "Link", 
   "options": "Department", 
   "permlevel": 0, 
   "print_hide": 0, 
   "print_hide_if_no_value": 0, 
   "read_only": 1, 
   "remember_last_selected_value": 0, 
   "report_hide": 0, 
   "reqd": 0, 
   "search_index": 0, 
   "set_only_once": 0, 
   "translatable": 0, 
   "unique": 0
  }, 
  {
   "allow_bulk_edit": 0, 
   "allow_in_quick_entry": 0, 
   "allow_on_submit": 0, 
   "bold": 0, 
   "collapsible": 0, 
   "columns": 0, 
   "depends_on": "eval:doc.designation", 
   "fetch_from": "employee.designation", 
   "fieldname": "designation", 
   "fieldtype": "Read Only", 
   "hidden": 0, 
   "ignore_user_permissions": 0, 
   "ignore_xss_filter": 0, 
   "in_filter": 0, 
   "in_global_search": 0, 
   "in_list_view": 0, 
   "in_standard_filter": 0, 
   "label": "Designation", 
   "length": 0, 
   "no_copy": 0, 
   "oldfieldname": "designation", 
   "oldfieldtype": "Link", 
   "options": "", 
   "permlevel": 0, 
   "print_hide": 0, 
   "print_hide_if_no_value": 0, 
   "read_only": 0, 
   "remember_last_selected_value": 0, 
   "report_hide": 0, 
   "reqd": 0, 
   "search_index": 0, 
   "set_only_once": 0, 
   "translatable": 0, 
   "unique": 0
  }, 
  {
   "allow_bulk_edit": 0, 
   "allow_in_quick_entry": 0, 
   "allow_on_submit": 0, 
   "bold": 0, 
   "collapsible": 0, 
   "columns": 0, 
   "fetch_from": "employee.branch", 
   "fieldname": "branch", 
   "fieldtype": "Read Only", 
   "hidden": 0, 
   "ignore_user_permissions": 0, 
   "ignore_xss_filter": 0, 
   "in_filter": 0, 
   "in_global_search": 0, 
   "in_list_view": 0, 
   "in_standard_filter": 1, 
   "label": "Branch", 
   "length": 0, 
   "no_copy": 0, 
   "oldfieldname": "branch", 
   "oldfieldtype": "Link", 
   "options": "", 
   "permlevel": 0, 
   "print_hide": 0, 
   "print_hide_if_no_value": 0, 
   "read_only": 0, 
   "remember_last_selected_value": 0, 
   "report_hide": 0, 
   "reqd": 0, 
   "search_index": 0, 
   "set_only_once": 0, 
   "translatable": 0, 
   "unique": 0
  }, 
  {
   "allow_bulk_edit": 0, 
   "allow_in_quick_entry": 0, 
   "allow_on_submit": 0, 
   "bold": 0, 
   "collapsible": 0, 
   "columns": 0, 
   "fieldname": "payroll_cost_center", 
   "fieldtype": "Link", 
   "hidden": 0, 
   "ignore_user_permissions": 0, 
   "ignore_xss_filter": 0, 
   "in_filter": 0, 
   "in_global_search": 0, 
   "in_list_view": 0, 
   "in_standard_filter": 0, 
   "label": "Payroll Cost Center", 
   "length": 0, 
   "no_copy": 0, 
   "options": "Cost Center", 
   "permlevel": 0, 
   "precision": "", 
   "print_hide": 0, 
   "print_hide_if_no_value": 0, 
   "read_only": 0, 
   "remember_last_selected_value": 0, 
   "report_hide": 0, 
   "reqd": 0, 
   "search_index": 0, 
   "set_only_once": 0, 
   "translatable": 0, 
   "unique": 0
  }, 
  {
   "allow_bulk_edit": 0, 
   "allow_in_quick_entry": 0, 
   "allow_on_submit": 0, 
   "bold": 0, 
   "collapsible": 0, 
   "columns": 0, 
   "fieldname": "column_break1", 
   "fieldtype": "Column Break", 
   "hidden": 0, 
   "ignore_user_permissions": 0, 
   "ignore_xss_filter": 0, 
   "in_filter": 0, 
   "in_global_search": 0, 
   "in_list_view": 0, 
   "in_standard_filter": 0, 
   "length": 0, 
   "no_copy": 0, 
   "oldfieldtype": "Column Break", 
   "permlevel": 0, 
   "print_hide": 0, 
   "print_hide_if_no_value": 0, 
   "read_only": 0, 
   "remember_last_selected_value": 0, 
   "report_hide": 0, 
   "reqd": 0, 
   "search_index": 0, 
   "set_only_once": 0, 
   "translatable": 0, 
   "unique": 0, 
   "width": "50%"
  }, 
  {
   "allow_bulk_edit": 0, 
   "allow_in_quick_entry": 0, 
   "allow_on_submit": 0, 
   "bold": 0, 
   "collapsible": 0, 
   "columns": 0, 
   "fieldname": "status", 
   "fieldtype": "Select", 
   "hidden": 0, 
   "ignore_user_permissions": 0, 
   "ignore_xss_filter": 0, 
   "in_filter": 0, 
   "in_global_search": 0, 
   "in_list_view": 0, 
   "in_standard_filter": 0, 
   "label": "Status", 
   "length": 0, 
   "no_copy": 0, 
   "options": "Draft\nSubmitted\nCancelled", 
   "permlevel": 0, 
   "precision": "", 
   "print_hide": 0, 
   "print_hide_if_no_value": 0, 
   "read_only": 1, 
   "remember_last_selected_value": 0, 
   "report_hide": 0, 
   "reqd": 0, 
   "search_index": 0, 
   "set_only_once": 0, 
   "translatable": 0, 
   "unique": 0
  }, 
  {
   "allow_bulk_edit": 0, 
   "allow_in_quick_entry": 0, 
   "allow_on_submit": 0, 
   "bold": 0, 
   "collapsible": 0, 
   "columns": 0, 
   "fieldname": "journal_entry", 
   "fieldtype": "Link", 
   "hidden": 0, 
   "ignore_user_permissions": 0, 
   "ignore_xss_filter": 0, 
   "in_filter": 0, 
   "in_global_search": 0, 
   "in_list_view": 0, 
   "in_standard_filter": 0, 
   "label": "Journal Entry", 
   "length": 0, 
   "no_copy": 0, 
   "options": "Journal Entry", 
   "permlevel": 0, 
   "precision": "", 
   "print_hide": 0, 
   "print_hide_if_no_value": 0, 
   "read_only": 1, 
   "remember_last_selected_value": 0, 
   "report_hide": 0, 
   "reqd": 0, 
   "search_index": 0, 
   "set_only_once": 0, 
   "translatable": 0, 
   "unique": 0
  }, 
  {
   "allow_bulk_edit": 0, 
   "allow_in_quick_entry": 0, 
   "allow_on_submit": 0, 
   "bold": 0, 
   "collapsible": 0, 
   "columns": 0, 
   "fieldname": "payroll_entry", 
   "fieldtype": "Link", 
   "hidden": 0, 
   "ignore_user_permissions": 0, 
   "ignore_xss_filter": 0, 
   "in_filter": 0, 
   "in_global_search": 0, 
   "in_list_view": 0, 
   "in_standard_filter": 0, 
   "label": "Payroll Entry", 
   "length": 0, 
   "no_copy": 0, 
   "options": "Payroll Entry", 
   "permlevel": 0, 
   "precision": "", 
   "print_hide": 0, 
   "print_hide_if_no_value": 0, 
   "read_only": 1, 
   "remember_last_selected_value": 0, 
   "report_hide": 0, 
   "reqd": 0, 
   "search_index": 0, 
   "set_only_once": 0, 
   "translatable": 0, 
   "unique": 0
  }, 
  {
   "allow_bulk_edit": 0, 
   "allow_in_quick_entry": 0, 
   "allow_on_submit": 0, 
   "bold": 0, 
   "collapsible": 0, 
   "columns": 0, 
   "fieldname": "company", 
   "fieldtype": "Link", 
   "hidden": 0, 
   "ignore_user_permissions": 0, 
   "ignore_xss_filter": 0, 
   "in_filter": 0, 
   "in_global_search": 0, 
   "in_list_view": 1, 
   "in_standard_filter": 1, 
   "label": "Company", 
   "length": 0, 
   "no_copy": 0, 
   "options": "Company", 
   "permlevel": 0, 
   "print_hide": 0, 
   "print_hide_if_no_value": 0, 
   "read_only": 0, 
   "remember_last_selected_value": 1, 
   "report_hide": 0, 
   "reqd": 1, 
   "search_index": 0, 
   "set_only_once": 0, 
   "translatable": 0, 
   "unique": 0
  }, 
  {
   "allow_bulk_edit": 0, 
   "allow_in_quick_entry": 0, 
   "allow_on_submit": 1, 
   "bold": 0, 
   "collapsible": 0, 
   "columns": 0, 
   "fieldname": "letter_head", 
   "fieldtype": "Link", 
   "hidden": 0, 
   "ignore_user_permissions": 1, 
   "ignore_xss_filter": 0, 
   "in_filter": 0, 
   "in_global_search": 0, 
   "in_list_view": 0, 
   "in_standard_filter": 0, 
   "label": "Letter Head", 
   "length": 0, 
   "no_copy": 0, 
   "options": "Letter Head", 
   "permlevel": 0, 
   "print_hide": 1, 
   "print_hide_if_no_value": 0, 
   "read_only": 0, 
   "remember_last_selected_value": 0, 
   "report_hide": 0, 
   "reqd": 0, 
   "search_index": 0, 
   "set_only_once": 0, 
   "translatable": 0, 
   "unique": 0
  }, 
  {
   "allow_bulk_edit": 0, 
   "allow_in_quick_entry": 0, 
   "allow_on_submit": 0, 
   "bold": 0, 
   "collapsible": 0, 
   "columns": 0, 
   "fieldname": "section_break_10", 
   "fieldtype": "Section Break", 
   "hidden": 0, 
   "ignore_user_permissions": 0, 
   "ignore_xss_filter": 0, 
   "in_filter": 0, 
   "in_global_search": 0, 
   "in_list_view": 0, 
   "in_standard_filter": 0, 
   "length": 0, 
   "no_copy": 0, 
   "permlevel": 0, 
   "precision": "", 
   "print_hide": 0, 
   "print_hide_if_no_value": 0, 
   "read_only": 0, 
   "remember_last_selected_value": 0, 
   "report_hide": 0, 
   "reqd": 0, 
   "search_index": 0, 
   "set_only_once": 0, 
   "translatable": 0, 
   "unique": 0
  }, 
  {
   "allow_bulk_edit": 0, 
   "allow_in_quick_entry": 0, 
   "allow_on_submit": 0, 
   "bold": 0, 
   "collapsible": 0, 
   "columns": 0, 
   "depends_on": "", 
   "fieldname": "salary_slip_based_on_timesheet", 
   "fieldtype": "Check", 
   "hidden": 0, 
   "ignore_user_permissions": 0, 
   "ignore_xss_filter": 0, 
   "in_filter": 0, 
   "in_global_search": 0, 
   "in_list_view": 0, 
   "in_standard_filter": 0, 
   "label": "Salary Slip Based on Timesheet", 
   "length": 0, 
   "no_copy": 0, 
   "options": "", 
   "permlevel": 0, 
   "precision": "", 
   "print_hide": 0, 
   "print_hide_if_no_value": 0, 
   "read_only": 1, 
   "remember_last_selected_value": 0, 
   "report_hide": 0, 
   "reqd": 0, 
   "search_index": 0, 
   "set_only_once": 0, 
   "translatable": 0, 
   "unique": 0
  }, 
  {
   "allow_bulk_edit": 0, 
   "allow_in_quick_entry": 0, 
   "allow_on_submit": 0, 
   "bold": 0, 
   "collapsible": 0, 
   "columns": 0, 
   "default": "", 
   "fieldname": "start_date", 
   "fieldtype": "Date", 
   "hidden": 0, 
   "ignore_user_permissions": 0, 
   "ignore_xss_filter": 0, 
   "in_filter": 0, 
   "in_global_search": 0, 
   "in_list_view": 0, 
   "in_standard_filter": 0, 
   "label": "Start Date", 
   "length": 0, 
   "no_copy": 0, 
   "permlevel": 0, 
   "precision": "", 
   "print_hide": 0, 
   "print_hide_if_no_value": 0, 
   "read_only": 0, 
   "remember_last_selected_value": 0, 
   "report_hide": 0, 
   "reqd": 0, 
   "search_index": 0, 
   "set_only_once": 0, 
   "translatable": 0, 
   "unique": 0
  }, 
  {
   "allow_bulk_edit": 0, 
   "allow_in_quick_entry": 0, 
   "allow_on_submit": 0, 
   "bold": 0, 
   "collapsible": 0, 
   "columns": 0, 
   "default": "", 
   "depends_on": "", 
   "fieldname": "end_date", 
   "fieldtype": "Date", 
   "hidden": 0, 
   "ignore_user_permissions": 0, 
   "ignore_xss_filter": 0, 
   "in_filter": 0, 
   "in_global_search": 0, 
   "in_list_view": 0, 
   "in_standard_filter": 0, 
   "label": "End Date", 
   "length": 0, 
   "no_copy": 0, 
   "permlevel": 0, 
   "precision": "", 
   "print_hide": 0, 
   "print_hide_if_no_value": 0, 
   "read_only": 0, 
   "remember_last_selected_value": 0, 
   "report_hide": 0, 
   "reqd": 0, 
   "search_index": 0, 
   "set_only_once": 0, 
   "translatable": 0, 
   "unique": 0
  }, 
  {
   "allow_bulk_edit": 0, 
   "allow_in_quick_entry": 0, 
   "allow_on_submit": 0, 
   "bold": 0, 
   "collapsible": 0, 
   "columns": 0, 
   "fieldname": "column_break_15", 
   "fieldtype": "Column Break", 
   "hidden": 0, 
   "ignore_user_permissions": 0, 
   "ignore_xss_filter": 0, 
   "in_filter": 0, 
   "in_global_search": 0, 
   "in_list_view": 0, 
   "in_standard_filter": 0, 
   "length": 0, 
   "no_copy": 0, 
   "permlevel": 0, 
   "precision": "", 
   "print_hide": 0, 
   "print_hide_if_no_value": 0, 
   "read_only": 0, 
   "remember_last_selected_value": 0, 
   "report_hide": 0, 
   "reqd": 0, 
   "search_index": 0, 
   "set_only_once": 0, 
   "translatable": 0, 
   "unique": 0
  }, 
  {
   "allow_bulk_edit": 0, 
   "allow_in_quick_entry": 0, 
   "allow_on_submit": 0, 
   "bold": 0, 
   "collapsible": 0, 
   "columns": 0, 
   "depends_on": "", 
   "fieldname": "salary_structure", 
   "fieldtype": "Link", 
   "hidden": 0, 
   "ignore_user_permissions": 0, 
   "ignore_xss_filter": 0, 
   "in_filter": 0, 
   "in_global_search": 0, 
   "in_list_view": 0, 
   "in_standard_filter": 0, 
   "label": "Salary Structure", 
   "length": 0, 
   "no_copy": 0, 
   "options": "Salary Structure", 
   "permlevel": 0, 
   "precision": "", 
   "print_hide": 0, 
   "print_hide_if_no_value": 0, 
   "read_only": 1, 
   "remember_last_selected_value": 0, 
   "report_hide": 0, 
   "reqd": 0, 
   "search_index": 0, 
   "set_only_once": 0, 
   "translatable": 0, 
   "unique": 0
  }, 
  {
   "allow_bulk_edit": 0, 
   "allow_in_quick_entry": 0, 
   "allow_on_submit": 0, 
   "bold": 0, 
   "collapsible": 0, 
   "columns": 0, 
   "default": "", 
   "depends_on": "eval:(!doc.salary_slip_based_on_timesheet)", 
   "fieldname": "payroll_frequency", 
   "fieldtype": "Select", 
   "hidden": 0, 
   "ignore_user_permissions": 0, 
   "ignore_xss_filter": 0, 
   "in_filter": 0, 
   "in_global_search": 0, 
   "in_list_view": 0, 
   "in_standard_filter": 0, 
   "label": "Payroll Frequency", 
   "length": 0, 
   "no_copy": 0, 
   "options": "\nMonthly\nFortnightly\nBimonthly\nWeekly\nDaily", 
   "permlevel": 0, 
   "precision": "", 
   "print_hide": 0, 
   "print_hide_if_no_value": 0, 
   "read_only": 0, 
   "remember_last_selected_value": 0, 
   "report_hide": 0, 
   "reqd": 0, 
   "search_index": 0, 
   "set_only_once": 0, 
   "translatable": 0, 
   "unique": 0
  }, 
  {
   "allow_bulk_edit": 0, 
   "allow_in_quick_entry": 0, 
   "allow_on_submit": 0, 
   "bold": 0, 
   "collapsible": 0, 
   "columns": 0, 
   "depends_on": "", 
   "fieldname": "total_working_days", 
   "fieldtype": "Float", 
   "hidden": 0, 
   "ignore_user_permissions": 0, 
   "ignore_xss_filter": 0, 
   "in_filter": 0, 
   "in_global_search": 0, 
   "in_list_view": 0, 
   "in_standard_filter": 0, 
   "label": "Working Days", 
   "length": 0, 
   "no_copy": 0, 
   "oldfieldname": "total_days_in_month", 
   "oldfieldtype": "Int", 
   "permlevel": 0, 
   "print_hide": 0, 
   "print_hide_if_no_value": 0, 
   "read_only": 1, 
   "remember_last_selected_value": 0, 
   "report_hide": 0, 
   "reqd": 1, 
   "search_index": 0, 
   "set_only_once": 0, 
   "translatable": 0, 
   "unique": 0
  }, 
  {
   "allow_bulk_edit": 0, 
   "allow_in_quick_entry": 0, 
   "allow_on_submit": 0, 
   "bold": 0, 
   "collapsible": 0, 
   "columns": 0, 
   "depends_on": "", 
   "fieldname": "leave_without_pay", 
   "fieldtype": "Float", 
   "hidden": 0, 
   "ignore_user_permissions": 0, 
   "ignore_xss_filter": 0, 
   "in_filter": 0, 
   "in_global_search": 0, 
   "in_list_view": 0, 
   "in_standard_filter": 0, 
   "label": "Leave Without Pay", 
   "length": 0, 
   "no_copy": 0, 
   "oldfieldname": "leave_without_pay", 
   "oldfieldtype": "Currency", 
   "permlevel": 0, 
   "print_hide": 0, 
   "print_hide_if_no_value": 0, 
   "read_only": 0, 
   "remember_last_selected_value": 0, 
   "report_hide": 0, 
   "reqd": 0, 
   "search_index": 0, 
   "set_only_once": 0, 
   "translatable": 0, 
   "unique": 0
  }, 
  {
   "allow_bulk_edit": 0, 
   "allow_in_quick_entry": 0, 
   "allow_on_submit": 0, 
   "bold": 0, 
   "collapsible": 0, 
   "columns": 0, 
   "depends_on": "", 
   "fieldname": "payment_days", 
   "fieldtype": "Float", 
   "hidden": 0, 
   "ignore_user_permissions": 0, 
   "ignore_xss_filter": 0, 
   "in_filter": 0, 
   "in_global_search": 0, 
   "in_list_view": 0, 
   "in_standard_filter": 0, 
   "label": "Payment Days", 
   "length": 0, 
   "no_copy": 0, 
   "oldfieldname": "payment_days", 
   "oldfieldtype": "Float", 
   "permlevel": 0, 
   "print_hide": 0, 
   "print_hide_if_no_value": 0, 
   "read_only": 1, 
   "remember_last_selected_value": 0, 
   "report_hide": 0, 
   "reqd": 1, 
   "search_index": 0, 
   "set_only_once": 0, 
   "translatable": 0, 
   "unique": 0
  }, 
  {
   "allow_bulk_edit": 0, 
   "allow_in_quick_entry": 0, 
   "allow_on_submit": 0, 
   "bold": 0, 
   "collapsible": 0, 
   "columns": 0, 
   "depends_on": "", 
   "fieldname": "hourly_wages", 
   "fieldtype": "Section Break", 
   "hidden": 0, 
   "ignore_user_permissions": 0, 
   "ignore_xss_filter": 0, 
   "in_filter": 0, 
   "in_global_search": 0, 
   "in_list_view": 0, 
   "in_standard_filter": 0, 
   "label": "", 
   "length": 0, 
   "no_copy": 0, 
   "permlevel": 0, 
   "precision": "", 
   "print_hide": 0, 
   "print_hide_if_no_value": 0, 
   "read_only": 0, 
   "remember_last_selected_value": 0, 
   "report_hide": 0, 
   "reqd": 0, 
   "search_index": 0, 
   "set_only_once": 0, 
   "translatable": 0, 
   "unique": 0
  }, 
  {
   "allow_bulk_edit": 0, 
   "allow_in_quick_entry": 0, 
   "allow_on_submit": 0, 
   "bold": 0, 
   "collapsible": 0, 
   "columns": 0, 
   "depends_on": "", 
   "fieldname": "timesheets", 
   "fieldtype": "Table", 
   "hidden": 0, 
   "ignore_user_permissions": 0, 
   "ignore_xss_filter": 0, 
   "in_filter": 0, 
   "in_global_search": 0, 
   "in_list_view": 0, 
   "in_standard_filter": 0, 
   "label": "Salary Slip Timesheet", 
   "length": 0, 
   "no_copy": 0, 
   "options": "Salary Slip Timesheet", 
   "permlevel": 0, 
   "precision": "", 
   "print_hide": 0, 
   "print_hide_if_no_value": 0, 
   "read_only": 0, 
   "remember_last_selected_value": 0, 
   "report_hide": 0, 
   "reqd": 0, 
   "search_index": 0, 
   "set_only_once": 0, 
   "translatable": 0, 
   "unique": 0
  }, 
  {
   "allow_bulk_edit": 0, 
   "allow_in_quick_entry": 0, 
   "allow_on_submit": 0, 
   "bold": 0, 
   "collapsible": 0, 
   "columns": 0, 
   "fieldname": "column_break_20", 
   "fieldtype": "Column Break", 
   "hidden": 0, 
   "ignore_user_permissions": 0, 
   "ignore_xss_filter": 0, 
   "in_filter": 0, 
   "in_global_search": 0, 
   "in_list_view": 0, 
   "in_standard_filter": 0, 
   "length": 0, 
   "no_copy": 0, 
   "permlevel": 0, 
   "precision": "", 
   "print_hide": 0, 
   "print_hide_if_no_value": 0, 
   "read_only": 0, 
   "remember_last_selected_value": 0, 
   "report_hide": 0, 
   "reqd": 0, 
   "search_index": 0, 
   "set_only_once": 0, 
   "translatable": 0, 
   "unique": 0
  }, 
  {
   "allow_bulk_edit": 0, 
   "allow_in_quick_entry": 0, 
   "allow_on_submit": 0, 
   "bold": 0, 
   "collapsible": 0, 
   "columns": 0, 
   "fieldname": "total_working_hours", 
   "fieldtype": "Float", 
   "hidden": 0, 
   "ignore_user_permissions": 0, 
   "ignore_xss_filter": 0, 
   "in_filter": 0, 
   "in_global_search": 0, 
   "in_list_view": 0, 
   "in_standard_filter": 0, 
   "label": "Total Working Hours", 
   "length": 0, 
   "no_copy": 0, 
   "permlevel": 0, 
   "precision": "", 
   "print_hide": 0, 
   "print_hide_if_no_value": 1, 
   "read_only": 0, 
   "remember_last_selected_value": 0, 
   "report_hide": 0, 
   "reqd": 0, 
   "search_index": 0, 
   "set_only_once": 0, 
   "translatable": 0, 
   "unique": 0
  }, 
  {
   "allow_bulk_edit": 0, 
   "allow_in_quick_entry": 0, 
   "allow_on_submit": 0, 
   "bold": 0, 
   "collapsible": 0, 
   "columns": 0, 
   "fieldname": "hour_rate", 
   "fieldtype": "Currency", 
   "hidden": 0, 
   "ignore_user_permissions": 0, 
   "ignore_xss_filter": 0, 
   "in_filter": 0, 
   "in_global_search": 0, 
   "in_list_view": 0, 
   "in_standard_filter": 0, 
   "label": "Hour Rate", 
   "length": 0, 
   "no_copy": 0, 
   "options": "Company:company:default_currency", 
   "permlevel": 0, 
   "precision": "2", 
   "print_hide": 0, 
   "print_hide_if_no_value": 1, 
   "read_only": 0, 
   "remember_last_selected_value": 0, 
   "report_hide": 0, 
   "reqd": 0, 
   "search_index": 0, 
   "set_only_once": 0, 
   "translatable": 0, 
   "unique": 0
  }, 
  {
   "allow_bulk_edit": 0, 
   "allow_in_quick_entry": 0, 
   "allow_on_submit": 0, 
   "bold": 0, 
   "collapsible": 0, 
   "columns": 0, 
   "depends_on": "", 
   "fieldname": "section_break_26", 
   "fieldtype": "Section Break", 
   "hidden": 0, 
   "ignore_user_permissions": 0, 
   "ignore_xss_filter": 0, 
   "in_filter": 0, 
   "in_global_search": 0, 
   "in_list_view": 0, 
   "in_standard_filter": 0, 
   "label": "", 
   "length": 0, 
   "no_copy": 0, 
   "permlevel": 0, 
   "precision": "", 
   "print_hide": 0, 
   "print_hide_if_no_value": 0, 
   "read_only": 0, 
   "remember_last_selected_value": 0, 
   "report_hide": 0, 
   "reqd": 0, 
   "search_index": 0, 
   "set_only_once": 0, 
   "translatable": 0, 
   "unique": 0
  }, 
  {
   "allow_bulk_edit": 0, 
   "allow_in_quick_entry": 0, 
   "allow_on_submit": 0, 
   "bold": 0, 
   "collapsible": 0, 
   "columns": 0, 
   "fieldname": "bank_name", 
   "fieldtype": "Data", 
   "hidden": 0, 
   "ignore_user_permissions": 0, 
   "ignore_xss_filter": 0, 
   "in_filter": 0, 
   "in_global_search": 0, 
   "in_list_view": 0, 
   "in_standard_filter": 0, 
   "label": "Bank Name", 
   "length": 0, 
   "no_copy": 0, 
   "oldfieldname": "bank_name", 
   "oldfieldtype": "Data", 
   "permlevel": 0, 
   "print_hide": 0, 
   "print_hide_if_no_value": 0, 
   "read_only": 1, 
   "remember_last_selected_value": 0, 
   "report_hide": 0, 
   "reqd": 0, 
   "search_index": 0, 
   "set_only_once": 0, 
   "translatable": 0, 
   "unique": 0
  }, 
  {
   "allow_bulk_edit": 0, 
   "allow_in_quick_entry": 0, 
   "allow_on_submit": 0, 
   "bold": 0, 
   "collapsible": 0, 
   "columns": 0, 
   "fieldname": "bank_account_no", 
   "fieldtype": "Data", 
   "hidden": 0, 
   "ignore_user_permissions": 0, 
   "ignore_xss_filter": 0, 
   "in_filter": 0, 
   "in_global_search": 0, 
   "in_list_view": 0, 
   "in_standard_filter": 0, 
   "label": "Bank Account No.", 
   "length": 0, 
   "no_copy": 0, 
   "oldfieldname": "bank_account_no", 
   "oldfieldtype": "Data", 
   "permlevel": 0, 
   "print_hide": 0, 
   "print_hide_if_no_value": 0, 
   "read_only": 1, 
   "remember_last_selected_value": 0, 
   "report_hide": 0, 
   "reqd": 0, 
   "search_index": 0, 
   "set_only_once": 0, 
   "translatable": 0, 
   "unique": 0
  }, 
  {
   "allow_bulk_edit": 0, 
   "allow_in_quick_entry": 0, 
   "allow_on_submit": 0, 
   "bold": 0, 
   "collapsible": 0, 
   "columns": 0, 
   "fieldname": "column_break_01", 
   "fieldtype": "Column Break", 
   "hidden": 0, 
   "ignore_user_permissions": 0, 
   "ignore_xss_filter": 0, 
   "in_filter": 0, 
   "in_global_search": 0, 
   "in_list_view": 0, 
   "in_standard_filter": 0, 
   "length": 0, 
   "no_copy": 0, 
   "permlevel": 0, 
   "precision": "", 
   "print_hide": 0, 
   "print_hide_if_no_value": 0, 
   "read_only": 0, 
   "remember_last_selected_value": 0, 
   "report_hide": 0, 
   "reqd": 0, 
   "search_index": 0, 
   "set_only_once": 0, 
   "translatable": 0, 
   "unique": 0
  }, 
  {
   "allow_bulk_edit": 0, 
   "allow_in_quick_entry": 0, 
   "allow_on_submit": 0, 
   "bold": 0, 
   "collapsible": 0, 
   "columns": 0, 
   "fieldname": "amended_from", 
   "fieldtype": "Link", 
   "hidden": 0, 
   "ignore_user_permissions": 1, 
   "ignore_xss_filter": 0, 
   "in_filter": 0, 
   "in_global_search": 0, 
   "in_list_view": 0, 
   "in_standard_filter": 0, 
   "label": "Amended From", 
   "length": 0, 
   "no_copy": 1, 
   "oldfieldname": "amended_from", 
   "oldfieldtype": "Data", 
   "options": "Salary Slip", 
   "permlevel": 0, 
   "print_hide": 1, 
   "print_hide_if_no_value": 0, 
   "read_only": 0, 
   "remember_last_selected_value": 0, 
   "report_hide": 0, 
   "reqd": 0, 
   "search_index": 0, 
   "set_only_once": 0, 
   "translatable": 0, 
   "unique": 0
  }, 
  {
   "allow_bulk_edit": 0, 
   "allow_in_quick_entry": 0, 
   "allow_on_submit": 0, 
   "bold": 0, 
   "collapsible": 0, 
   "columns": 0, 
   "fieldname": "section_break_32", 
   "fieldtype": "Section Break", 
   "hidden": 0, 
   "ignore_user_permissions": 0, 
   "ignore_xss_filter": 0, 
   "in_filter": 0, 
   "in_global_search": 0, 
   "in_list_view": 0, 
   "in_standard_filter": 0, 
   "length": 0, 
   "no_copy": 0, 
   "permlevel": 0, 
   "precision": "", 
   "print_hide": 0, 
   "print_hide_if_no_value": 0, 
   "read_only": 0, 
   "remember_last_selected_value": 0, 
   "report_hide": 0, 
   "reqd": 0, 
   "search_index": 0, 
   "set_only_once": 0, 
   "translatable": 0, 
   "unique": 0
  }, 
  {
   "allow_bulk_edit": 0, 
   "allow_in_quick_entry": 0, 
   "allow_on_submit": 0, 
   "bold": 0, 
   "collapsible": 0, 
   "columns": 0, 
   "fieldname": "deduct_tax_for_unclaimed_employee_benefits", 
   "fieldtype": "Check", 
   "hidden": 0, 
   "ignore_user_permissions": 0, 
   "ignore_xss_filter": 0, 
   "in_filter": 0, 
   "in_global_search": 0, 
   "in_list_view": 0, 
   "in_standard_filter": 0, 
   "label": "Deduct Tax For Unclaimed Employee Benefits", 
   "length": 0, 
   "no_copy": 0, 
   "permlevel": 0, 
   "precision": "", 
   "print_hide": 0, 
   "print_hide_if_no_value": 0, 
   "read_only": 0, 
   "remember_last_selected_value": 0, 
   "report_hide": 0, 
   "reqd": 0, 
   "search_index": 0, 
   "set_only_once": 0, 
   "translatable": 0, 
   "unique": 0
  }, 
  {
   "allow_bulk_edit": 0, 
   "allow_in_quick_entry": 0, 
   "allow_on_submit": 0, 
   "bold": 0, 
   "collapsible": 0, 
   "columns": 0, 
   "fieldname": "deduct_tax_for_unsubmitted_tax_exemption_proof", 
   "fieldtype": "Check", 
   "hidden": 0, 
   "ignore_user_permissions": 0, 
   "ignore_xss_filter": 0, 
   "in_filter": 0, 
   "in_global_search": 0, 
   "in_list_view": 0, 
   "in_standard_filter": 0, 
   "label": "Deduct Tax For Unsubmitted Tax Exemption Proof", 
   "length": 0, 
   "no_copy": 0, 
   "permlevel": 0, 
   "precision": "", 
   "print_hide": 0, 
   "print_hide_if_no_value": 0, 
   "read_only": 0, 
   "remember_last_selected_value": 0, 
   "report_hide": 0, 
   "reqd": 0, 
   "search_index": 0, 
   "set_only_once": 0, 
   "translatable": 0, 
   "unique": 0
  }, 
  {
   "allow_bulk_edit": 0, 
   "allow_in_quick_entry": 0, 
   "allow_on_submit": 0, 
   "bold": 0, 
   "collapsible": 0, 
   "columns": 0, 
   "fieldname": "earning_deduction", 
   "fieldtype": "Section Break", 
   "hidden": 0, 
   "ignore_user_permissions": 0, 
   "ignore_xss_filter": 0, 
   "in_filter": 0, 
   "in_global_search": 0, 
   "in_list_view": 0, 
   "in_standard_filter": 0, 
   "label": "Earning & Deduction", 
   "length": 0, 
   "no_copy": 0, 
   "oldfieldtype": "Section Break", 
   "permlevel": 0, 
   "print_hide": 0, 
   "print_hide_if_no_value": 0, 
   "read_only": 0, 
   "remember_last_selected_value": 0, 
   "report_hide": 0, 
   "reqd": 0, 
   "search_index": 0, 
   "set_only_once": 0, 
   "translatable": 0, 
   "unique": 0
  }, 
  {
   "allow_bulk_edit": 0, 
   "allow_in_quick_entry": 0, 
   "allow_on_submit": 0, 
   "bold": 0, 
   "collapsible": 0, 
   "columns": 0, 
   "fieldname": "earning", 
   "fieldtype": "Column Break", 
   "hidden": 0, 
   "ignore_user_permissions": 0, 
   "ignore_xss_filter": 0, 
   "in_filter": 0, 
   "in_global_search": 0, 
   "in_list_view": 0, 
   "in_standard_filter": 0, 
   "label": "Earning", 
   "length": 0, 
   "no_copy": 0, 
   "oldfieldtype": "Column Break", 
   "permlevel": 0, 
   "print_hide": 0, 
   "print_hide_if_no_value": 0, 
   "read_only": 0, 
   "remember_last_selected_value": 0, 
   "report_hide": 0, 
   "reqd": 0, 
   "search_index": 0, 
   "set_only_once": 0, 
   "translatable": 0, 
   "unique": 0, 
   "width": "50%"
  }, 
  {
   "allow_bulk_edit": 0, 
   "allow_in_quick_entry": 0, 
   "allow_on_submit": 0, 
   "bold": 0, 
   "collapsible": 0, 
   "columns": 0, 
   "depends_on": "", 
   "fieldname": "earnings", 
   "fieldtype": "Table", 
   "hidden": 0, 
   "ignore_user_permissions": 0, 
   "ignore_xss_filter": 0, 
   "in_filter": 0, 
   "in_global_search": 0, 
   "in_list_view": 0, 
   "in_standard_filter": 0, 
   "label": "Earnings", 
   "length": 0, 
   "no_copy": 0, 
   "oldfieldname": "earning_details", 
   "oldfieldtype": "Table", 
   "options": "Salary Detail", 
   "permlevel": 0, 
   "print_hide": 0, 
   "print_hide_if_no_value": 0, 
   "read_only": 0, 
   "remember_last_selected_value": 0, 
   "report_hide": 0, 
   "reqd": 0, 
   "search_index": 0, 
   "set_only_once": 0, 
   "translatable": 0, 
   "unique": 0
  }, 
  {
   "allow_bulk_edit": 0, 
   "allow_in_quick_entry": 0, 
   "allow_on_submit": 0, 
   "bold": 0, 
   "collapsible": 0, 
   "columns": 0, 
   "fieldname": "deduction", 
   "fieldtype": "Column Break", 
   "hidden": 0, 
   "ignore_user_permissions": 0, 
   "ignore_xss_filter": 0, 
   "in_filter": 0, 
   "in_global_search": 0, 
   "in_list_view": 0, 
   "in_standard_filter": 0, 
   "label": "Deduction", 
   "length": 0, 
   "no_copy": 0, 
   "oldfieldtype": "Column Break", 
   "permlevel": 0, 
   "print_hide": 0, 
   "print_hide_if_no_value": 0, 
   "read_only": 0, 
   "remember_last_selected_value": 0, 
   "report_hide": 0, 
   "reqd": 0, 
   "search_index": 0, 
   "set_only_once": 0, 
   "translatable": 0, 
   "unique": 0, 
   "width": "50%"
  }, 
  {
   "allow_bulk_edit": 0, 
   "allow_in_quick_entry": 0, 
   "allow_on_submit": 0, 
   "bold": 0, 
   "collapsible": 0, 
   "columns": 0, 
   "fieldname": "deductions", 
   "fieldtype": "Table", 
   "hidden": 0, 
   "ignore_user_permissions": 0, 
   "ignore_xss_filter": 0, 
   "in_filter": 0, 
   "in_global_search": 0, 
   "in_list_view": 0, 
   "in_standard_filter": 0, 
   "label": "Deductions", 
   "length": 0, 
   "no_copy": 0, 
   "oldfieldname": "deduction_details", 
   "oldfieldtype": "Table", 
   "options": "Salary Detail", 
   "permlevel": 0, 
   "print_hide": 0, 
   "print_hide_if_no_value": 0, 
   "read_only": 0, 
   "remember_last_selected_value": 0, 
   "report_hide": 0, 
   "reqd": 0, 
   "search_index": 0, 
   "set_only_once": 0, 
   "translatable": 0, 
   "unique": 0
  }, 
  {
   "allow_bulk_edit": 0, 
   "allow_in_quick_entry": 0, 
   "allow_on_submit": 0, 
   "bold": 0, 
   "collapsible": 0, 
   "columns": 0, 
   "fieldname": "totals", 
   "fieldtype": "Section Break", 
   "hidden": 0, 
   "ignore_user_permissions": 0, 
   "ignore_xss_filter": 0, 
   "in_filter": 0, 
   "in_global_search": 0, 
   "in_list_view": 0, 
   "in_standard_filter": 0, 
   "label": "", 
   "length": 0, 
   "no_copy": 0, 
   "oldfieldtype": "Section Break", 
   "permlevel": 0, 
   "print_hide": 0, 
   "print_hide_if_no_value": 0, 
   "read_only": 0, 
   "remember_last_selected_value": 0, 
   "report_hide": 0, 
   "reqd": 0, 
   "search_index": 0, 
   "set_only_once": 0, 
   "translatable": 0, 
   "unique": 0
  }, 
  {
   "allow_bulk_edit": 0, 
   "allow_in_quick_entry": 0, 
   "allow_on_submit": 0, 
   "bold": 0, 
   "collapsible": 0, 
   "columns": 0, 
   "fieldname": "gross_pay", 
   "fieldtype": "Currency", 
   "hidden": 0, 
   "ignore_user_permissions": 0, 
   "ignore_xss_filter": 0, 
   "in_filter": 0, 
   "in_global_search": 0, 
   "in_list_view": 0, 
   "in_standard_filter": 0, 
   "label": "Gross Pay", 
   "length": 0, 
   "no_copy": 0, 
   "oldfieldname": "gross_pay", 
   "oldfieldtype": "Currency", 
   "options": "Company:company:default_currency", 
   "permlevel": 0, 
   "print_hide": 0, 
   "print_hide_if_no_value": 0, 
   "read_only": 1, 
   "remember_last_selected_value": 0, 
   "report_hide": 0, 
   "reqd": 0, 
   "search_index": 0, 
   "set_only_once": 0, 
   "translatable": 0, 
   "unique": 0
  }, 
  {
   "allow_bulk_edit": 0, 
   "allow_in_quick_entry": 0, 
   "allow_on_submit": 0, 
   "bold": 0, 
   "collapsible": 0, 
   "columns": 0, 
   "fieldname": "column_break_25", 
   "fieldtype": "Column Break", 
   "hidden": 0, 
   "ignore_user_permissions": 0, 
   "ignore_xss_filter": 0, 
   "in_filter": 0, 
   "in_global_search": 0, 
   "in_list_view": 0, 
   "in_standard_filter": 0, 
   "length": 0, 
   "no_copy": 0, 
   "permlevel": 0, 
   "print_hide": 0, 
   "print_hide_if_no_value": 0, 
   "read_only": 0, 
   "remember_last_selected_value": 0, 
   "report_hide": 0, 
   "reqd": 0, 
   "search_index": 0, 
   "set_only_once": 0, 
   "translatable": 0, 
   "unique": 0
  }, 
  {
   "allow_bulk_edit": 0, 
   "allow_in_quick_entry": 0, 
   "allow_on_submit": 0, 
   "bold": 0, 
   "collapsible": 0, 
   "columns": 0, 
   "fieldname": "total_deduction", 
   "fieldtype": "Currency", 
   "hidden": 0, 
   "ignore_user_permissions": 0, 
   "ignore_xss_filter": 0, 
   "in_filter": 0, 
   "in_global_search": 0, 
   "in_list_view": 0, 
   "in_standard_filter": 0, 
   "label": "Total Deduction", 
   "length": 0, 
   "no_copy": 0, 
   "oldfieldname": "total_deduction", 
   "oldfieldtype": "Currency", 
   "options": "Company:company:default_currency", 
   "permlevel": 0, 
   "print_hide": 0, 
   "print_hide_if_no_value": 0, 
   "read_only": 1, 
   "remember_last_selected_value": 0, 
   "report_hide": 0, 
   "reqd": 0, 
   "search_index": 0, 
   "set_only_once": 0, 
   "translatable": 0, 
   "unique": 0
  }, 
  {
   "allow_bulk_edit": 0, 
   "allow_in_quick_entry": 0, 
   "allow_on_submit": 0, 
   "bold": 0, 
   "collapsible": 0, 
   "columns": 0, 
   "depends_on": "total_loan_repayment", 
   "fieldname": "loan_repayment", 
   "fieldtype": "Section Break", 
   "hidden": 0, 
   "ignore_user_permissions": 0, 
   "ignore_xss_filter": 0, 
   "in_filter": 0, 
   "in_global_search": 0, 
   "in_list_view": 0, 
   "in_standard_filter": 0, 
   "label": "Loan repayment", 
   "length": 0, 
   "no_copy": 0, 
   "permlevel": 0, 
   "precision": "", 
   "print_hide": 0, 
   "print_hide_if_no_value": 0, 
   "read_only": 0, 
   "remember_last_selected_value": 0, 
   "report_hide": 0, 
   "reqd": 0, 
   "search_index": 0, 
   "set_only_once": 0, 
   "translatable": 0, 
   "unique": 0
  }, 
  {
   "allow_bulk_edit": 0, 
   "allow_in_quick_entry": 0, 
   "allow_on_submit": 0, 
   "bold": 0, 
   "collapsible": 0, 
   "columns": 0, 
   "fieldname": "loans", 
   "fieldtype": "Table", 
   "hidden": 0, 
   "ignore_user_permissions": 0, 
   "ignore_xss_filter": 0, 
   "in_filter": 0, 
   "in_global_search": 0, 
   "in_list_view": 0, 
   "in_standard_filter": 0, 
   "label": "Employee Loan", 
   "length": 0, 
   "no_copy": 0, 
   "options": "Salary Slip Loan", 
   "permlevel": 0, 
   "precision": "", 
   "print_hide": 1, 
   "print_hide_if_no_value": 0, 
   "read_only": 1, 
   "remember_last_selected_value": 0, 
   "report_hide": 0, 
   "reqd": 0, 
   "search_index": 0, 
   "set_only_once": 0, 
   "translatable": 0, 
   "unique": 0
  }, 
  {
   "allow_bulk_edit": 0, 
   "allow_in_quick_entry": 0, 
   "allow_on_submit": 0, 
   "bold": 0, 
   "collapsible": 0, 
   "columns": 0, 
   "fieldname": "section_break_43", 
   "fieldtype": "Section Break", 
   "hidden": 0, 
   "ignore_user_permissions": 0, 
   "ignore_xss_filter": 0, 
   "in_filter": 0, 
   "in_global_search": 0, 
   "in_list_view": 0, 
   "in_standard_filter": 0, 
   "length": 0, 
   "no_copy": 0, 
   "permlevel": 0, 
   "precision": "", 
   "print_hide": 0, 
   "print_hide_if_no_value": 0, 
   "read_only": 0, 
   "remember_last_selected_value": 0, 
   "report_hide": 0, 
   "reqd": 0, 
   "search_index": 0, 
   "set_only_once": 0, 
   "translatable": 0, 
   "unique": 0
  }, 
  {
   "allow_bulk_edit": 0, 
   "allow_in_quick_entry": 0, 
   "allow_on_submit": 0, 
   "bold": 0, 
   "collapsible": 0, 
   "columns": 0, 
   "default": "0", 
   "fieldname": "total_principal_amount", 
   "fieldtype": "Currency", 
   "hidden": 0, 
   "ignore_user_permissions": 0, 
   "ignore_xss_filter": 0, 
   "in_filter": 0, 
   "in_global_search": 0, 
   "in_list_view": 0, 
   "in_standard_filter": 0, 
   "label": "Total Principal Amount", 
   "length": 0, 
   "no_copy": 0, 
   "options": "Company:company:default_currency", 
   "permlevel": 0, 
   "precision": "", 
   "print_hide": 0, 
   "print_hide_if_no_value": 0, 
   "read_only": 1, 
   "remember_last_selected_value": 0, 
   "report_hide": 0, 
   "reqd": 0, 
   "search_index": 0, 
   "set_only_once": 0, 
   "translatable": 0, 
   "unique": 0
  }, 
  {
   "allow_bulk_edit": 0, 
   "allow_in_quick_entry": 0, 
   "allow_on_submit": 0, 
   "bold": 0, 
   "collapsible": 0, 
   "columns": 0, 
   "default": "0", 
   "fieldname": "total_interest_amount", 
   "fieldtype": "Currency", 
   "hidden": 0, 
   "ignore_user_permissions": 0, 
   "ignore_xss_filter": 0, 
   "in_filter": 0, 
   "in_global_search": 0, 
   "in_list_view": 0, 
   "in_standard_filter": 0, 
   "label": "Total Interest Amount", 
   "length": 0, 
   "no_copy": 0, 
   "options": "Company:company:default_currency", 
   "permlevel": 0, 
   "precision": "", 
   "print_hide": 0, 
   "print_hide_if_no_value": 0, 
   "read_only": 1, 
   "remember_last_selected_value": 0, 
   "report_hide": 0, 
   "reqd": 0, 
   "search_index": 0, 
   "set_only_once": 0, 
   "translatable": 0, 
   "unique": 0
  }, 
  {
   "allow_bulk_edit": 0, 
   "allow_in_quick_entry": 0, 
   "allow_on_submit": 0, 
   "bold": 0, 
   "collapsible": 0, 
   "columns": 0, 
   "fieldname": "column_break_45", 
   "fieldtype": "Column Break", 
   "hidden": 0, 
   "ignore_user_permissions": 0, 
   "ignore_xss_filter": 0, 
   "in_filter": 0, 
   "in_global_search": 0, 
   "in_list_view": 0, 
   "in_standard_filter": 0, 
   "length": 0, 
   "no_copy": 0, 
   "permlevel": 0, 
   "precision": "", 
   "print_hide": 0, 
   "print_hide_if_no_value": 0, 
   "read_only": 0, 
   "remember_last_selected_value": 0, 
   "report_hide": 0, 
   "reqd": 0, 
   "search_index": 0, 
   "set_only_once": 0, 
   "translatable": 0, 
   "unique": 0
  }, 
  {
   "allow_bulk_edit": 0, 
   "allow_in_quick_entry": 0, 
   "allow_on_submit": 0, 
   "bold": 0, 
   "collapsible": 0, 
   "columns": 0, 
   "default": "0", 
   "fieldname": "total_loan_repayment", 
   "fieldtype": "Currency", 
   "hidden": 0, 
   "ignore_user_permissions": 0, 
   "ignore_xss_filter": 0, 
   "in_filter": 0, 
   "in_global_search": 0, 
   "in_list_view": 0, 
   "in_standard_filter": 0, 
   "label": "Total Loan Repayment", 
   "length": 0, 
   "no_copy": 0, 
   "options": "Company:company:default_currency", 
   "permlevel": 0, 
   "precision": "", 
   "print_hide": 0, 
   "print_hide_if_no_value": 0, 
   "read_only": 1, 
   "remember_last_selected_value": 0, 
   "report_hide": 0, 
   "reqd": 0, 
   "search_index": 0, 
   "set_only_once": 0, 
   "translatable": 0, 
   "unique": 0
  }, 
  {
   "allow_bulk_edit": 0, 
   "allow_in_quick_entry": 0, 
   "allow_on_submit": 0, 
   "bold": 0, 
   "collapsible": 0, 
   "columns": 0, 
   "fieldname": "net_pay_info", 
   "fieldtype": "Section Break", 
   "hidden": 0, 
   "ignore_user_permissions": 0, 
   "ignore_xss_filter": 0, 
   "in_filter": 0, 
   "in_global_search": 0, 
   "in_list_view": 0, 
   "in_standard_filter": 0, 
   "label": "net pay info", 
   "length": 0, 
   "no_copy": 0, 
   "permlevel": 0, 
   "precision": "", 
   "print_hide": 0, 
   "print_hide_if_no_value": 0, 
   "read_only": 0, 
   "remember_last_selected_value": 0, 
   "report_hide": 0, 
   "reqd": 0, 
   "search_index": 0, 
   "set_only_once": 0, 
   "translatable": 0, 
   "unique": 0
  }, 
  {
   "allow_bulk_edit": 0, 
   "allow_in_quick_entry": 0, 
   "allow_on_submit": 0, 
   "bold": 0, 
   "collapsible": 0, 
   "columns": 0, 
   "description": "Gross Pay - Total Deduction - Loan Repayment", 
   "fieldname": "net_pay", 
   "fieldtype": "Currency", 
   "hidden": 0, 
   "ignore_user_permissions": 0, 
   "ignore_xss_filter": 0, 
   "in_filter": 0, 
   "in_global_search": 0, 
   "in_list_view": 0, 
   "in_standard_filter": 0, 
   "label": "Net Pay", 
   "length": 0, 
   "no_copy": 0, 
   "oldfieldname": "net_pay", 
   "oldfieldtype": "Currency", 
   "options": "Company:company:default_currency", 
   "permlevel": 0, 
   "print_hide": 0, 
   "print_hide_if_no_value": 0, 
   "read_only": 1, 
   "remember_last_selected_value": 0, 
   "report_hide": 0, 
   "reqd": 0, 
   "search_index": 0, 
   "set_only_once": 0, 
   "translatable": 0, 
   "unique": 0
  }, 
  {
   "allow_bulk_edit": 0, 
   "allow_in_quick_entry": 0, 
   "allow_on_submit": 0, 
   "bold": 0, 
   "collapsible": 0, 
   "columns": 0, 
   "fieldname": "column_break_53", 
   "fieldtype": "Column Break", 
   "hidden": 0, 
   "ignore_user_permissions": 0, 
   "ignore_xss_filter": 0, 
   "in_filter": 0, 
   "in_global_search": 0, 
   "in_list_view": 0, 
   "in_standard_filter": 0, 
   "length": 0, 
   "no_copy": 0, 
   "permlevel": 0, 
   "precision": "", 
   "print_hide": 0, 
   "print_hide_if_no_value": 0, 
   "read_only": 0, 
   "remember_last_selected_value": 0, 
   "report_hide": 0, 
   "reqd": 0, 
   "search_index": 0, 
   "set_only_once": 0, 
   "translatable": 0, 
   "unique": 0
  }, 
  {
   "allow_bulk_edit": 0, 
   "allow_in_quick_entry": 0, 
   "allow_on_submit": 0, 
   "bold": 1, 
   "collapsible": 0, 
   "columns": 0, 
   "fieldname": "rounded_total", 
   "fieldtype": "Currency", 
   "hidden": 0, 
   "ignore_user_permissions": 0, 
   "ignore_xss_filter": 0, 
   "in_filter": 0, 
   "in_global_search": 0, 
   "in_list_view": 0, 
   "in_standard_filter": 0, 
   "label": "Rounded Total", 
   "length": 0, 
   "no_copy": 0, 
   "options": "Company:company:default_currency", 
   "permlevel": 0, 
   "print_hide": 0, 
   "print_hide_if_no_value": 0, 
   "read_only": 1, 
   "remember_last_selected_value": 0, 
   "report_hide": 0, 
   "reqd": 0, 
   "search_index": 0, 
   "set_only_once": 0, 
   "translatable": 0, 
   "unique": 0
  }, 
  {
   "allow_bulk_edit": 0, 
   "allow_in_quick_entry": 0, 
   "allow_on_submit": 0, 
   "bold": 0, 
   "collapsible": 0, 
   "columns": 0, 
   "fieldname": "section_break_55", 
   "fieldtype": "Section Break", 
   "hidden": 0, 
   "ignore_user_permissions": 0, 
   "ignore_xss_filter": 0, 
   "in_filter": 0, 
   "in_global_search": 0, 
   "in_list_view": 0, 
   "in_standard_filter": 0, 
   "length": 0, 
   "no_copy": 0, 
   "permlevel": 0, 
   "precision": "", 
   "print_hide": 0, 
   "print_hide_if_no_value": 0, 
   "read_only": 0, 
   "remember_last_selected_value": 0, 
   "report_hide": 0, 
   "reqd": 0, 
   "search_index": 0, 
   "set_only_once": 0, 
   "translatable": 0, 
   "unique": 0
  }, 
  {
   "allow_bulk_edit": 0, 
   "allow_in_quick_entry": 0, 
   "allow_on_submit": 0, 
   "bold": 0, 
   "collapsible": 0, 
   "columns": 0, 
   "description": "Net Pay (in words) will be visible once you save the Salary Slip.", 
   "fieldname": "total_in_words", 
   "fieldtype": "Data", 
   "hidden": 0, 
   "ignore_user_permissions": 0, 
   "ignore_xss_filter": 0, 
   "in_filter": 0, 
   "in_global_search": 0, 
   "in_list_view": 0, 
   "in_standard_filter": 0, 
   "label": "Total in words", 
   "length": 0, 
   "no_copy": 0, 
   "oldfieldname": "net_pay_in_words", 
   "oldfieldtype": "Data", 
   "permlevel": 0, 
   "print_hide": 0, 
   "print_hide_if_no_value": 0, 
   "read_only": 1, 
   "remember_last_selected_value": 0, 
   "report_hide": 0, 
   "reqd": 0, 
   "search_index": 0, 
   "set_only_once": 0, 
   "translatable": 0, 
   "unique": 0
  }
 ], 
 "has_web_view": 0, 
 "hide_heading": 0, 
 "hide_toolbar": 0, 
 "icon": "fa fa-file-text", 
 "idx": 9, 
 "image_view": 0, 
 "in_create": 0, 
 "is_submittable": 1, 
 "issingle": 0, 
 "istable": 0, 
 "max_attachments": 0, 
 "modified": "2019-01-04 12:55:20.263180", 
 "modified_by": "Administrator", 
 "module": "HR", 
 "name": "Salary Slip", 
 "owner": "Administrator", 
 "permissions": [
  {
   "amend": 0, 
   "cancel": 0, 
   "create": 1, 
   "delete": 0, 
   "email": 1, 
   "export": 0, 
   "if_owner": 0, 
   "import": 0, 
   "permlevel": 0, 
   "print": 1, 
   "read": 1, 
   "report": 1, 
   "role": "HR User", 
   "set_user_permissions": 0, 
   "share": 1, 
   "submit": 1, 
   "write": 1
  }, 
  {
   "amend": 1, 
   "cancel": 1, 
   "create": 1, 
   "delete": 1, 
   "email": 1, 
   "export": 0, 
   "if_owner": 0, 
   "import": 0, 
   "permlevel": 0, 
   "print": 1, 
   "read": 1, 
   "report": 1, 
   "role": "HR Manager", 
   "set_user_permissions": 0, 
   "share": 1, 
   "submit": 1, 
   "write": 1
  }, 
  {
   "amend": 0, 
   "cancel": 0, 
   "create": 0, 
   "delete": 0, 
   "email": 0, 
   "export": 0, 
   "if_owner": 0, 
   "import": 0, 
   "permlevel": 0, 
   "print": 0, 
   "read": 1, 
   "report": 0, 
   "role": "Employee", 
   "set_user_permissions": 0, 
   "share": 0, 
   "submit": 0, 
   "write": 0
  }
 ], 
 "quick_entry": 0, 
 "read_only": 0, 
 "read_only_onload": 0, 
 "show_name_in_global_search": 1, 
 "sort_field": "modified", 
 "sort_order": "DESC", 
 "timeline_field": "employee", 
 "title_field": "employee_name", 
 "track_changes": 0, 
 "track_seen": 0, 
 "track_views": 0
}