{
 "allow_copy": 0, 
 "allow_import": 0, 
 "allow_rename": 0, 
 "creation": "2014-07-23 15:12:27.746665", 
 "custom": 0, 
 "docstatus": 0, 
 "doctype": "DocType", 
 "document_type": "", 
 "fields": [
  {
   "fieldname": "sec_break1", 
   "fieldtype": "Section Break", 
   "label": "Party Details", 
   "permlevel": 0
  }, 
  {
   "fieldname": "company", 
   "fieldtype": "Link", 
   "label": "Company", 
   "options": "Company", 
   "permlevel": 0, 
   "reqd": 1
  }, 
  {
   "allow_on_submit": 0, 
   "default": "Customer", 
   "fieldname": "party_type", 
   "fieldtype": "Select", 
   "hidden": 0, 
   "ignore_user_permissions": 0, 
   "in_filter": 0, 
   "in_list_view": 1, 
   "label": "Party Type", 
   "no_copy": 0, 
   "options": "Customer\nSupplier", 
   "permlevel": 0, 
   "print_hide": 0, 
   "read_only": 0, 
   "report_hide": 0, 
   "reqd": 1, 
   "search_index": 0, 
   "set_only_once": 0
  }, 
  {
   "allow_on_submit": 0, 
   "depends_on": "eval:(doc.party_type == 'Customer')", 
   "fieldname": "customer", 
   "fieldtype": "Link", 
   "hidden": 0, 
   "ignore_user_permissions": 0, 
   "in_filter": 0, 
   "in_list_view": 1, 
   "label": "Customer", 
   "no_copy": 0, 
   "options": "Customer", 
   "permlevel": 0, 
   "print_hide": 0, 
   "read_only": 0, 
   "report_hide": 0, 
   "reqd": 0, 
   "search_index": 0, 
   "set_only_once": 0
  }, 
  {
   "allow_on_submit": 0, 
   "depends_on": "eval:(doc.party_type == 'Supplier')", 
   "fieldname": "supplier", 
   "fieldtype": "Link", 
   "hidden": 0, 
   "ignore_user_permissions": 0, 
   "in_filter": 0, 
   "in_list_view": 1, 
   "label": "Supplier", 
   "no_copy": 0, 
   "options": "Supplier", 
   "permlevel": 0, 
   "print_hide": 0, 
   "read_only": 0, 
   "report_hide": 0, 
   "reqd": 0, 
   "search_index": 0, 
   "set_only_once": 0
  }, 
  {
   "fieldname": "party_account", 
   "fieldtype": "Link", 
   "hidden": 1, 
   "label": "Party Account", 
   "no_copy": 1, 
   "options": "Account", 
   "permlevel": 0, 
   "read_only": 1
  }, 
  {
   "allow_on_submit": 0, 
   "fieldname": "received_or_paid", 
   "fieldtype": "Select", 
   "hidden": 0, 
   "ignore_user_permissions": 0, 
   "in_filter": 0, 
   "in_list_view": 1, 
   "label": "Received Or Paid", 
   "no_copy": 0, 
   "options": "Received\nPaid", 
   "permlevel": 0, 
   "print_hide": 0, 
   "read_only": 0, 
   "report_hide": 0, 
   "reqd": 1, 
   "search_index": 0, 
   "set_only_once": 0
  }, 
  {
   "allow_on_submit": 0, 
   "fieldname": "get_outstanding_vouchers", 
   "fieldtype": "Button", 
   "hidden": 0, 
   "ignore_user_permissions": 0, 
   "in_filter": 0, 
   "in_list_view": 0, 
   "label": "Get Outstanding Vouchers", 
   "no_copy": 0, 
   "permlevel": 0, 
   "print_hide": 0, 
   "read_only": 0, 
   "report_hide": 0, 
   "reqd": 0, 
   "search_index": 0, 
   "set_only_once": 0
  }, 
  {
   "allow_on_submit": 0, 
   "fieldname": "col_break1", 
   "fieldtype": "Column Break", 
   "hidden": 0, 
   "ignore_user_permissions": 0, 
   "in_filter": 0, 
   "in_list_view": 0, 
   "label": "Column Break 1", 
   "no_copy": 0, 
   "permlevel": 0, 
   "print_hide": 0, 
   "read_only": 0, 
   "report_hide": 0, 
   "reqd": 0, 
   "search_index": 0, 
   "set_only_once": 0
  }, 
  {
   "allow_on_submit": 0, 
   "fieldname": "payment_mode", 
   "fieldtype": "Link", 
   "hidden": 0, 
   "ignore_user_permissions": 0, 
   "in_filter": 0, 
   "in_list_view": 0, 
   "label": "Payment Mode", 
   "no_copy": 0, 
   "options": "Mode of Payment", 
   "permlevel": 0, 
   "print_hide": 0, 
   "read_only": 0, 
   "report_hide": 0, 
   "reqd": 0, 
   "search_index": 0, 
   "set_only_once": 0
  }, 
  {
   "allow_on_submit": 0, 
   "fieldname": "payment_account", 
   "fieldtype": "Link", 
   "hidden": 0, 
   "ignore_user_permissions": 0, 
   "in_filter": 0, 
   "in_list_view": 0, 
   "label": "Payment Account", 
   "no_copy": 0, 
   "options": "Account", 
   "permlevel": 0, 
   "print_hide": 0, 
   "read_only": 0, 
   "report_hide": 0, 
   "reqd": 0, 
   "search_index": 0, 
   "set_only_once": 0
  }, 
  {
   "allow_on_submit": 0, 
   "fieldname": "reference_no", 
   "fieldtype": "Data", 
   "hidden": 0, 
   "ignore_user_permissions": 0, 
   "in_filter": 0, 
   "in_list_view": 0, 
   "label": "Reference No", 
   "no_copy": 0, 
   "permlevel": 0, 
   "print_hide": 0, 
   "read_only": 0, 
   "report_hide": 0, 
   "reqd": 0, 
   "search_index": 0, 
   "set_only_once": 0
  }, 
  {
   "allow_on_submit": 0, 
   "fieldname": "reference_date", 
   "fieldtype": "Date", 
   "hidden": 0, 
   "ignore_user_permissions": 0, 
   "in_filter": 0, 
   "in_list_view": 0, 
   "label": "Reference Date", 
   "no_copy": 0, 
   "permlevel": 0, 
   "print_hide": 0, 
   "read_only": 0, 
   "report_hide": 0, 
   "reqd": 0, 
   "search_index": 0, 
   "set_only_once": 0
  }, 
  {
   "allow_on_submit": 0, 
   "depends_on": "eval:(doc.company && doc.party_type && doc.received_or_paid && (doc.customer || doc.supplier))", 
   "fieldname": "sec_break3", 
   "fieldtype": "Section Break", 
   "hidden": 0, 
   "ignore_user_permissions": 0, 
   "in_filter": 0, 
   "in_list_view": 0, 
   "label": "Against Voucher", 
   "no_copy": 0, 
   "permlevel": 0, 
   "print_hide": 0, 
   "read_only": 0, 
   "report_hide": 0, 
   "reqd": 0, 
   "search_index": 0, 
   "set_only_once": 0
  }, 
  {
   "allow_on_submit": 0, 
   "fieldname": "payment_tool_details", 
   "fieldtype": "Table", 
   "hidden": 0, 
   "ignore_user_permissions": 0, 
   "in_filter": 0, 
   "in_list_view": 0, 
   "label": "Payment Tool Details", 
   "no_copy": 0, 
   "options": "Payment Tool Detail", 
   "permlevel": 0, 
   "print_hide": 0, 
   "read_only": 0, 
   "report_hide": 0, 
   "reqd": 0, 
   "search_index": 0, 
   "set_only_once": 0
  }, 
  {
   "depends_on": "eval:(doc.company && doc.party_type && doc.received_or_paid && (doc.customer || doc.supplier))", 
   "fieldname": "section_break_19", 
   "fieldtype": "Section Break", 
   "permlevel": 0, 
   "precision": ""
  }, 
  {
   "fieldname": "total_payment_amount", 
   "fieldtype": "Currency", 
   "label": "Total Payment Amount", 
   "permlevel": 0, 
   "read_only": 1
  }, 
  {
   "allow_on_submit": 0, 
   "fieldname": "make_journal_voucher", 
   "fieldtype": "Button", 
   "hidden": 0, 
   "ignore_user_permissions": 0, 
   "in_filter": 0, 
   "in_list_view": 0, 
   "label": "Make Journal Voucher", 
   "no_copy": 0, 
   "permlevel": 0, 
   "print_hide": 0, 
   "read_only": 0, 
   "report_hide": 0, 
   "reqd": 0, 
   "search_index": 0, 
   "set_only_once": 0
  }, 
  {
   "fieldname": "data_22", 
   "fieldtype": "Column Break", 
   "permlevel": 0, 
   "precision": ""
  }, 
  {
   "depends_on": "eval:(doc.company && doc.party_type && doc.received_or_paid && (doc.customer || doc.supplier))", 
   "fieldname": "section_break_21", 
   "fieldtype": "Section Break", 
   "permlevel": 0, 
   "precision": ""
  }, 
  {
   "allow_on_submit": 0, 
   "fieldname": "make_jv_help", 
   "fieldtype": "Small Text", 
   "hidden": 0, 
   "ignore_user_permissions": 0, 
   "in_filter": 0, 
   "in_list_view": 0, 
   "no_copy": 0, 
   "permlevel": 0, 
   "print_hide": 0, 
   "read_only": 1, 
   "report_hide": 0, 
   "reqd": 0, 
   "search_index": 0, 
   "set_only_once": 0
  }
 ], 
 "hide_heading": 0, 
 "hide_toolbar": 1, 
 "icon": "icon-magic", 
 "in_create": 0, 
 "in_dialog": 0, 
 "is_submittable": 0, 
 "issingle": 1, 
 "istable": 0, 
 "modified": "2014-09-12 04:43:05.963218", 
 "modified_by": "Administrator", 
 "module": "Accounts", 
 "name": "Payment Tool", 
 "name_case": "", 
 "owner": "Administrator", 
 "permissions": [
  {
   "amend": 0, 
   "apply_user_permissions": 0, 
   "cancel": 0, 
   "create": 1, 
   "delete": 0, 
   "email": 0, 
   "export": 0, 
   "import": 0, 
   "permlevel": 0, 
   "print": 0, 
   "read": 1, 
   "report": 0, 
   "role": "Accounts Manager", 
   "set_user_permissions": 0, 
   "submit": 0, 
   "write": 1
  }, 
  {
   "amend": 0, 
   "apply_user_permissions": 0, 
   "cancel": 0, 
   "create": 1, 
   "delete": 0, 
   "email": 0, 
   "export": 0, 
   "import": 0, 
   "permlevel": 0, 
   "print": 0, 
   "read": 1, 
   "report": 0, 
   "role": "Accounts User", 
   "set_user_permissions": 0, 
   "submit": 0, 
   "write": 1
  }
 ], 
 "read_only": 0, 
 "read_only_onload": 0, 
 "sort_field": "modified", 
 "sort_order": "DESC"
}