{
 "actions": [],
 "creation": "2022-10-19 13:42:15.248931",
 "doctype": "DocType",
 "editable_grid": 1,
 "engine": "InnoDB",
 "field_order": [
  "branch",
  "supplier",
  "column_break1",
  "from_date",
  "to_date",
  "bank_name",
  "column_break2",
  "account_number",
  "ifs_code",
  "reference_document"
 ],
 "fields": [
  {
   "fieldname": "branch",
   "fieldtype": "Link",
   "in_list_view": 1,
   "label": "Branch",
   "options": "Branch",
   "reqd": 1
  },
  {
   "fieldname": "supplier",
   "fieldtype": "Link",
   "in_list_view": 1,
   "label": "Owner",
   "options": "Supplier",
   "read_only": 1
  },
  {
   "fieldname": "column_break1",
   "fieldtype": "Column Break"
  },
  {
   "fieldname": "from_date",
   "fieldtype": "Date",
   "in_list_view": 1,
   "label": "From Date",
   "read_only": 1
  },
  {
   "fieldname": "to_date",
   "fieldtype": "Date",
   "in_list_view": 1,
   "label": "To Date",
   "read_only": 1
  },
  {
   "fieldname": "bank_name",
   "fieldtype": "Data",
   "label": "Bank Name",
   "read_only": 1
  },
  {
   "fieldname": "column_break2",
   "fieldtype": "Column Break"
  },
  {
   "fieldname": "account_number",
   "fieldtype": "Data",
   "label": "Account Number",
   "read_only": 1
  },
  {
   "fieldname": "ifs_code",
   "fieldtype": "Data",
   "label": "IFS Code",
   "read_only": 1
  },
  {
   "fieldname": "reference_document",
   "fieldtype": "Data",
   "hidden": 1,
   "label": "Reference Document"
  }
 ],
 "index_web_pages_for_search": 1,
 "istable": 1,
 "links": [],
 "modified": "2022-11-27 20:49:55.509952",
 "modified_by": "Administrator",
 "module": "Fleet Management",
 "name": "Equipment History",
 "owner": "Administrator",
 "permissions": [],
 "sort_field": "modified",
 "sort_order": "DESC",
 "states": []
}